{
  "version": "7",
  "dialect": "sqlite",
  "entries": [
    {
      "idx": 0,
      "version": "6",
      "when": 1784616846310,
      "tag": "0000_careless_captain_america",
      "breakpoints": true
    },
    {
      "idx": 1,
      "version": "6",
      "when": 1784618831129,
      "tag": "0001_charming_callisto",
      "breakpoints": true
    },
    {
      "idx": 2,
      "version": "6",
      "when": 1784620832072,
      "tag": "0002_purple_molecule_man",
      "breakpoints": true
    }
  ]
}